vis_sample/__init__.py
vis_sample/classes.py
vis_sample/constants.py
vis_sample/file_handling.py
vis_sample/gridding.py
vis_sample/interpolation.py
vis_sample/transforms.py
vis_sample/vis_sampler.py
vis_sample-0.3.3.dist-info/LICENSE
vis_sample-0.3.3.dist-info/METADATA
vis_sample-0.3.3.dist-info/WHEEL
vis_sample-0.3.3.dist-info/top_level.txt
vis_sample-0.3.3.dist-info/RECORD
