Metadata-Version: 1.1
Name: vis-sample
Version: 0.3.3
Summary: Visibility sampler
Home-page: https://github.com/AstroChem/vis_sample
Author: Ryan Loomis
Author-email: rloomis@nrao.edu
License: MIT
Keywords: astronomy science
Platform: UNKNOWN
Classifier: Development Status :: 5 - Production/Stable
Classifier: Environment :: Console
Classifier: Intended Audience :: Science/Research
Classifier: License :: OSI Approved :: MIT License
Classifier: Operating System :: OS Independent
Classifier: Programming Language :: Python :: 3
Classifier: Programming Language :: Python :: 3.6
Classifier: Topic :: Scientific/Engineering :: Astronomy
